LICENSE
MANIFEST.in
README.rst
setup.py
arrayFilter/__init__.py
arrayFilter/_allele.py
arrayFilter/_compareGroup.py
arrayFilter/_core.py
arrayFilter/_exception.py
arrayFilter/_filter_cli.py
arrayFilter/_public_cli.py
arrayFilter/_utils.py
arrayFilter/_var.py
arrayFilter/array_plot.R
arrayFilter/params.cfg
gmArrayFilter.egg-info/PKG-INFO
gmArrayFilter.egg-info/SOURCES.txt
gmArrayFilter.egg-info/dependency_links.txt
gmArrayFilter.egg-info/requires.txt
gmArrayFilter.egg-info/top_level.txt
scripts/gmArray
test/__init__.py
test/test_allele.py