Metadata-Version: 1.1
Name: gmArrayFilter
Version: 1.0.3
Summary: A python package to filter SNP array data
Home-page: https://gitee.com/brightrock/plant-gmap-array
Author: lx Gui
Author-email: guilixuan@gmail.com
License: MIT
Keywords: bioinformatics,NGS,Reseq,SNP
Platform: all
Classifier: Intended Audience :: Developers
Classifier: Operating System :: OS Independent
Classifier: Natural Language :: Chinese (Simplified)
Classifier: Programming Language :: Python
Classifier: Programming Language :: Python :: 3.6
Classifier: Programming Language :: Python :: 3.7
Classifier: Programming Language :: Python :: 3.8
